atptools/__init__.py
atptools/c_py.py
atptools/csv.py
atptools/csv_object.py
atptools/dataset.py
atptools/dataset_ts_long.py
atptools/dataset_ts_long_polars.py
atptools/dict_default.py
atptools/histogram.py
atptools/records.py
atptools/utils.py
atptools/dataframe/__init__.py
atptools/dataframe/description.py
atptools/dataframe/index/__init__.py
atptools/dataframe/index/process_func.py
atptools/dataframe/series/__init__.py
atptools/dataframe/series/process_func.py
atptools/dataframe/series_ts/__init__.py
atptools/dataframe/series_ts/process_func.py
atptools/io/__init__.py
atptools/io/aio.py
atptools/io/io.py
atptools/process_components/__init__.py
atptools/process_components/counters.py
atptools-0.2.31.dist-info/licenses/LICENSE
atptools-0.2.31.dist-info/METADATA
atptools-0.2.31.dist-info/WHEEL
atptools-0.2.31.dist-info/top_level.txt
atptools-0.2.31.dist-info/RECORD
