Metadata-Version: 2.4
Name: atptools
Version: 0.2.31
Summary: Dataset manipulation tool.
Author-email: Andraz Polak <andrazpolak@gmail.com>
Project-URL: homepage, https://github.com/atp-things/pkgpy-atp-tools
Project-URL: repository, https://github.com/atp-things/pkgpy-atp-tools
Project-URL: PyPI, https://pypi.org/project/atptools/
Keywords: records,csv,dataset,measurement,list,json,yaml,pandas
Classifier: Programming Language :: Python
Classifier: Programming Language :: Python :: 3
Classifier: Operating System :: OS Independent
Requires-Python: >=3.11
License-File: LICENSE
Requires-Dist: toml
Requires-Dist: types-toml
Requires-Dist: pyyaml
Requires-Dist: types-pyyaml
Requires-Dist: pandas
Requires-Dist: pandas-stubs
Requires-Dist: aiofiles
Requires-Dist: fastapi
Requires-Dist: pydantic
Dynamic: license-file
